{
  "persons" : [
    {
      "addr" : "北京昌平1",
      "age" : 18,
      "name" : "孙行者1",
      "sex" : "男1"
    },
    {
      "addr" : "北京昌平2",
      "age" : 19,
      "name" : "孙行者2",
      "sex" : "男2"
    },
    {
      "addr" : "北京昌平3",
      "age" : 20,
      "name" : "孙行者3",
      "sex" : "男3"
    },
    {
      "addr" : "北京昌平4",
      "age" : 21,
      "name" : "孙行者4",
      "sex" : "男4"
    },
    {
      "addr" : "北京昌平5",
      "age" : 22,
      "name" : "孙行者5",
      "sex" : "男5"
    },
    {
      "addr" : "北京昌平1",
      "age" : 18,
      "name" : "行者孙1",
      "sex" : "男1"
    },
    {
      "addr" : "北京昌平2",
      "age" : 19,
      "name" : "行者孙2",
      "sex" : "男2"
    },
    {
      "addr" : "北京昌平3",
      "age" : 20,
      "name" : "行者孙3",
      "sex" : "男3"
    },
    {
      "addr" : "北京昌平4",
      "age" : 21,
      "name" : "行者孙4",
      "sex" : "男4"
    },
    {
      "addr" : "北京昌平5",
      "age" : 22,
      "name" : "行者孙5",
      "sex" : "男5"
    },
    {
      "addr" : "北京昌平1",
      "age" : 18,
      "name" : "者行孙1",
      "sex" : "男1"
    },
    {
      "addr" : "北京昌平2",
      "age" : 19,
      "name" : "者行孙2",
      "sex" : "男2"
    },
    {
      "addr" : "北京昌平3",
      "age" : 20,
      "name" : "者行孙3",
      "sex" : "男3"
    },
    {
      "addr" : "北京昌平4",
      "age" : 21,
      "name" : "者行孙4",
      "sex" : "男4"
    },
    {
      "addr" : "北京昌平5",
      "age" : 22,
      "name" : "者行孙5",
      "sex" : "男5"
    },
    {
      "addr" : "北京昌平1",
      "age" : 18,
      "name" : "者孙行1",
      "sex" : "男1"
    },
    {
      "addr" : "北京昌平2",
      "age" : 19,
      "name" : "者孙行2",
      "sex" : "男2"
    },
    {
      "addr" : "北京昌平3",
      "age" : 20,
      "name" : "者孙行3",
      "sex" : "男3"
    },
    {
      "addr" : "北京昌平4",
      "age" : 21,
      "name" : "者孙行4",
      "sex" : "男4"
    },
    {
      "addr" : "北京昌平5",
      "age" : 22,
      "name" : "者孙行5",
      "sex" : "男5"
    },
    {
      "addr" : "北京昌平1",
      "age" : 22,
      "name" : "行孙者1",
      "sex" : "男1"
    },
    {
      "addr" : "北京昌平2",
      "age" : 22,
      "name" : "行孙者2",
      "sex" : "男2"
    },
    {
      "addr" : "北京昌平3",
      "age" : 22,
      "name" : "行孙者3",
      "sex" : "男3"
    }
  ],
  "totalCount" : 23
}